setup.py
EvilSample/__init__.py
EvilSample.egg-info/PKG-INFO
EvilSample.egg-info/SOURCES.txt
EvilSample.egg-info/dependency_links.txt
EvilSample.egg-info/not-zip-safe
EvilSample.egg-info/top_level.txt