Metadata-Version: 1.0
Name: EvilSample
Version: 0.1
Summary: Save it.
Home-page: http://mad.com
Author: Flying Circus
Author-email: joe@example.com
License: BPUT
Platform: UNKNOWN
